{
	"configurations" : 
	[
		{
			"directories" : 
			[
				{
					"build" : ".",
					"jsonFile" : "directory-.-Debug-f5ebdc15457944623624.json",
					"minimumCMakeVersion" : 
					{
						"string" : "3.22"
					},
					"projectIndex" : 0,
					"source" : ".",
					"targetIndexes" : 
					[
						0,
						1,
						2,
						3,
						4,
						5
					]
				}
			],
			"name" : "Debug",
			"projects" : 
			[
				{
					"directoryIndexes" : 
					[
						0
					],
					"name" : "rayTracer",
					"targetIndexes" : 
					[
						0,
						1,
						2,
						3,
						4,
						5
					]
				}
			],
			"targets" : 
			[
				{
					"directoryIndex" : 0,
					"id" : "display::@6890427a1f51a3e7e1df",
					"jsonFile" : "target-display-Debug-29eb3ec89f509b13285e.json",
					"name" : "display",
					"projectIndex" : 0
				},
				{
					"directoryIndex" : 0,
					"id" : "imageWriter::@6890427a1f51a3e7e1df",
					"jsonFile" : "target-imageWriter-Debug-3007180d9796dd53792c.json",
					"name" : "imageWriter",
					"projectIndex" : 0
				},
				{
					"directoryIndex" : 0,
					"id" : "images::@6890427a1f51a3e7e1df",
					"jsonFile" : "target-images-Debug-3ee8a563230edc67aad9.json",
					"name" : "images",
					"projectIndex" : 0
				},
				{
					"directoryIndex" : 0,
					"id" : "lights::@6890427a1f51a3e7e1df",
					"jsonFile" : "target-lights-Debug-25bf389a0a81bbc72eb7.json",
					"name" : "lights",
					"projectIndex" : 0
				},
				{
					"directoryIndex" : 0,
					"id" : "primitives::@6890427a1f51a3e7e1df",
					"jsonFile" : "target-primitives-Debug-9e7089f78667645ac50a.json",
					"name" : "primitives",
					"projectIndex" : 0
				},
				{
					"directoryIndex" : 0,
					"id" : "shapes::@6890427a1f51a3e7e1df",
					"jsonFile" : "target-shapes-Debug-e4e4d1e0ab287a1d7937.json",
					"name" : "shapes",
					"projectIndex" : 0
				}
			]
		}
	],
	"kind" : "codemodel",
	"paths" : 
	{
		"build" : "/Users/juanperez/documents/projects/ray-tracer/build",
		"source" : "/Users/juanperez/documents/projects/ray-tracer"
	},
	"version" : 
	{
		"major" : 2,
		"minor" : 3
	}
}
